autonomous_recovery_agent/__init__.py
autonomous_recovery_agent/agent.py
autonomous_recovery_agent/cli.py
autonomous_recovery_agent/config.py
autonomous_recovery_agent/config_manager.py
autonomous_recovery_agent/flask_integration.py
autonomous_recovery_agent/mongodb_integration.py
autonomous_recovery_agent/setup.py
autonomous_recovery_agent/web_ui.py
autonomous_recovery_agent/alerts/alert_manager.py
autonomous_recovery_agent/alerts/email_alert.py
autonomous_recovery_agent/flask_mongodb_app/app.py
autonomous_recovery_agent/flask_mongodb_app/examples/basic_usage.py
autonomous_recovery_agent/maintenance/manager.py
autonomous_recovery_agent/monitoring/__init__.py
autonomous_recovery_agent/monitoring/database_monitor.py
autonomous_recovery_agent/monitoring/disk_monitor.py
autonomous_recovery_agent/monitoring/service_monitor.py
autonomous_recovery_agent/recovery/__init__.py
autonomous_recovery_agent/recovery/engine.py
autonomous_recovery_agent/templates/dashboard.html
autonomous_recovery_agent/traffic/__init__.py
autonomous_recovery_agent/traffic/throttler.py
autonomous_recovery_agent/utils/logging.py
autonomous_recovery_agent-3.2.5.dist-info/METADATA
autonomous_recovery_agent-3.2.5.dist-info/WHEEL
autonomous_recovery_agent-3.2.5.dist-info/entry_points.txt
autonomous_recovery_agent-3.2.5.dist-info/top_level.txt
autonomous_recovery_agent-3.2.5.dist-info/RECORD
